Metadata-Version: 2.1
Name: hhsh
Version: 0.1.1
Summary: 能不能好好说话？ cli
Home-page: https://github.com/yihong0618/hhsh
Author: itorr,yihong0618
Author-email: zouzou0208@gmail.com
License: UNKNOWN
Keywords: python hhsh cli terminal
Platform: UNKNOWN
Classifier: Development Status :: 4 - Beta
Classifier: Environment :: Console
Classifier: Intended Audience :: Developers
Classifier: Operating System :: OS Independent
Classifier: Programming Language :: Python :: 3.6
Classifier: Programming Language :: Python :: 3.7
Classifier: Programming Language :: Python :: 3.8
Classifier: Topic :: Software Development :: Libraries
License-File: LICENSE
